ringtail/__init__.py
ringtail/cloptionparser.py
ringtail/exceptions.py
ringtail/interactions.py
ringtail/logutils.py
ringtail/mpmanager.py
ringtail/mpreaderwriter.py
ringtail/outputmanager.py
ringtail/parsers.py
ringtail/receptormanager.py
ringtail/resultsmanager.py
ringtail/ringtailcore.py
ringtail/ringtailoptions.py
ringtail/storagemanager.py
ringtail/util.py
ringtail/cli/__init__.py
ringtail/cli/rt_compare.py
ringtail/cli/rt_db_to_v200.py
ringtail/cli/rt_db_v100_to_v110.py
ringtail/cli/rt_generate_config_file.py
ringtail/cli/rt_process_vs.py
ringtail-2.2.0.dist-info/licenses/LICENSE
ringtail-2.2.0.dist-info/METADATA
ringtail-2.2.0.dist-info/WHEEL
ringtail-2.2.0.dist-info/entry_points.txt
ringtail-2.2.0.dist-info/top_level.txt
ringtail-2.2.0.dist-info/RECORD
