Metadata-Version: 2.4
Name: ringtail
Version: 2.2.0
Summary: Package for creating database from virtual screening files and performing filtering on results.
Home-page: https://github.com/forlilab/Ringtail
Author: Forli Lab
Author-email: forli@scripps.edu
License: L-GPL-v2.1
Keywords: virtual screening,molecular modeling,drug discovery,drug design,docking,autodock
Classifier: Environment :: Console
Classifier: Environment :: Other Environment
Classifier: Intended Audience :: Education
Classifier: Intended Audience :: Science/Research
Classifier: License :: OSI Approved :: GNU Lesser General Public License v2 or later (LGPLv2+)
Classifier: Natural Language :: English
Classifier: Operating System :: MacOS
Classifier: Operating System :: POSIX :: Linux
Classifier: Programming Language :: Python :: 3.9
Classifier: Topic :: Scientific/Engineering :: Bio-Informatics
Classifier: Topic :: Scientific/Engineering :: Chemistry
Classifier: Topic :: Software Development :: Libraries
License-File: LICENSE
Dynamic: author
Dynamic: author-email
Dynamic: classifier
Dynamic: description
Dynamic: description-content-type
Dynamic: home-page
Dynamic: keywords
Dynamic: license
Dynamic: license-file
Dynamic: summary
